querystring_parser/__init__.py
querystring_parser/builder.py
querystring_parser/parser.py
querystring_parser/tests.py
sw_querystring_parser-2.0.0.dist-info/LICENSE
sw_querystring_parser-2.0.0.dist-info/METADATA
sw_querystring_parser-2.0.0.dist-info/WHEEL
sw_querystring_parser-2.0.0.dist-info/top_level.txt
sw_querystring_parser-2.0.0.dist-info/RECORD
