Metadata-Version: 2.1
Name: sw-querystring_parser
Version: 2.0.0
Summary: QueryString parser for Python/Django that correctly handles nested dictionaries
Home-page: https://github.com/bernii/querystring-parser
Author: bernii
Author-email: berni@extensa.pl
Classifier: Development Status :: 6 - Mature
Classifier: License :: OSI Approved :: MIT License
Classifier: Operating System :: OS Independent
Classifier: Programming Language :: Python :: 3
License-File: LICENSE
